cbr_static/__init__.py
cbr_static/assets/cbr/account-circle.svg
cbr_static/assets/cbr/cbr-logo-beta.png
cbr_static/assets/cbr/cbr-logo-community.png
cbr_static/assets/cbr/generic-user-pic.png
cbr_static/assets/cbr/notes
cbr_static/assets/cbr/tcb-favicon.png
cbr_static/assets/css/icons/font-awesome/css/fontawesome-all.css
cbr_static/assets/css/icons/font-awesome/css/fontawesome-all.min.css
cbr_static/assets/css/icons/font-awesome/webfonts/fa-solid-900.eot
cbr_static/assets/css/icons/font-awesome/webfonts/fa-solid-900.svg
cbr_static/assets/css/icons/font-awesome/webfonts/fa-solid-900.ttf
cbr_static/assets/css/icons/font-awesome/webfonts/fa-solid-900.woff
cbr_static/assets/css/icons/font-awesome/webfonts/fa-solid-900.woff2
cbr_static/assets/css/icons/material-design-iconic-font/css/materialdesignicons.min.css
cbr_static/assets/css/icons/material-design-iconic-font/fonts/materialdesignicons-webfont.ttf
cbr_static/assets/css/icons/material-design-iconic-font/fonts/materialdesignicons-webfont.woff
cbr_static/assets/css/icons/material-design-iconic-font/fonts/materialdesignicons-webfont.woff2
cbr_static/assets/css/icons/simple-line-icons/css/simple-line-icons.css
cbr_static/assets/css/icons/themify-icons/fonts/themify.ttf
cbr_static/assets/css/icons/themify-icons/fonts/themify.woff
cbr_static/assets/css/icons/themify-icons/themify-icons.css
cbr_static/assets/css/style.cbr-fixes.css
cbr_static/assets/css/style.min.css
cbr_static/assets/dev/img/200x200.png
cbr_static/assets/dev/img/400x200.png
cbr_static/assets/dev/img/400x300.png
cbr_static/assets/dev/img/800x400.png
cbr_static/assets/dev/img/notes.txt
cbr_static/assets/fonts/poppins-v21-latin-regular.woff2
cbr_static/assets/js/app-style-switcher.js
cbr_static/assets/js/custom.js
cbr_static/assets/js/sidebarmenu.js
cbr_static/assets/js/waves.js
cbr_static/assets/plugins/bootstrap/dist/js/bootstrap.bundle.min.js
cbr_static/assets/plugins/data-tables/css/dataTables.dataTables.min.css
cbr_static-0.7.18.dist-info/LICENSE
cbr_static-0.7.18.dist-info/METADATA
cbr_static-0.7.18.dist-info/WHEEL
cbr_static-0.7.18.dist-info/RECORD
